planterbox/__init__.py
planterbox/decorators.py
planterbox/exceptions.py
planterbox/feature.py
planterbox/parsing.py
planterbox/plugin.py
planterbox/summarize.py
planterbox/util.py
planterbox/tests/__init__.py
planterbox/tests/test_parse_feature.py
planterbox/tests/test_plugin.py
planterbox/tests/test_scenario_test_case.py
planterbox/tests/test_feature/__init__.py
planterbox/tests/test_hooks/__init__.py
planterbox/tests/test_hooks_examples/__init__.py
planterbox-0.7.2.dist-info/LICENSE
planterbox-0.7.2.dist-info/METADATA
planterbox-0.7.2.dist-info/WHEEL
planterbox-0.7.2.dist-info/top_level.txt
planterbox-0.7.2.dist-info/zip-safe
planterbox-0.7.2.dist-info/RECORD
