Metadata-Version: 2.1
Name: planterbox
Version: 0.7.2
Summary: A plugin for nose2 implementing behavior-driven testing.
Home-page: https://github.com/npilon/planterbox
Author: Nick Pilon
Author-email: npilon@gmail.com
License: MIT
Keywords: testing test bdd lettuce cucumber gherkin nosetests nose2
Platform: UNKNOWN
Classifier: Intended Audience :: Developers
Classifier: Topic :: Software Development :: Testing
Classifier: Programming Language :: Python
Classifier: Programming Language :: Python :: 2.7
Classifier: Programming Language :: Python :: 3.5
Classifier: Programming Language :: Python :: 3.6
Classifier: Programming Language :: Python :: 3.7
Requires-Dist: nose2 (>=0.6.0)
Requires-Dist: mock
Requires-Dist: six
